{
  "best_metric": null,
  "best_model_checkpoint": null,
  "epoch": 3.0,
  "global_step": 2064,
  "is_hyper_param_search": false,
  "is_local_process_zero": true,
  "is_world_process_zero": true,
  "log_history": [
    {
      "epoch": 0.7267441860465116,
      "learning_rate": 3.788759689922481e-05,
      "loss": 1.981723388671875,
      "step": 500
    },
    {
      "epoch": 1.4534883720930232,
      "learning_rate": 2.5775193798449615e-05,
      "loss": 1.7634595947265626,
      "step": 1000
    },
    {
      "epoch": 2.1802325581395348,
      "learning_rate": 1.3662790697674418e-05,
      "loss": 1.6614154052734376,
      "step": 1500
    },
    {
      "epoch": 2.9069767441860463,
      "learning_rate": 1.550387596899225e-06,
      "loss": 1.61123486328125,
      "step": 2000
    },
    {
      "epoch": 3.0,
      "step": 2064,
      "train_runtime": 869.1081,
      "train_samples_per_second": 2.375
    }
  ],
  "max_steps": 2064,
  "num_train_epochs": 3,
  "total_flos": 1578048084246528,
  "trial_name": null,
  "trial_params": null
}
